sphinxcontrib/sass.py
sphinxcontrib_sass-0.3.3.dist-info/LICENSE
sphinxcontrib_sass-0.3.3.dist-info/WHEEL
sphinxcontrib_sass-0.3.3.dist-info/METADATA
sphinxcontrib_sass-0.3.3.dist-info/RECORD
