Metadata-Version: 2.1
Name: sphinxcontrib-sass
Version: 0.3.3
Summary: Sphinx extension to compile sass to css in running sphinx-build.
Author-email: Kazuya Takei <myself@attakei.net>
Classifier: Development Status :: 3 - Alpha
Classifier: Framework :: Sphinx
Classifier: Framework :: Sphinx :: Extension
Classifier: Intended Audience :: Developers
Classifier: License :: OSI Approved :: Apache Software License
Classifier: Programming Language :: Python :: 3.7
Classifier: Programming Language :: Python :: 3.8
Classifier: Programming Language :: Python :: 3.9
Classifier: Programming Language :: Python :: 3.10
Classifier: Topic :: Documentation :: Sphinx
Requires-Dist: Sphinx
Requires-Dist: libsass
Requires-Dist: black >=22.3.0,<23 ; extra == "test"
Requires-Dist: flake8 >=3.8.4,<4 ; extra == "test"
Requires-Dist: pytest >=6.2.2,<7 ; extra == "test"
Project-URL: Home, https://github.com/attakei-lab/sphinxcontrib-sass
Project-URL: Source, https://github.com/attakei-lab/sphinxcontrib-sass
Provides-Extra: test
